deepexperiment/__init__.py
deepexperiment/deepexperiment.py
deepexperiment-0.1.0.dist-info/METADATA
deepexperiment-0.1.0.dist-info/WHEEL
deepexperiment-0.1.0.dist-info/top_level.txt
deepexperiment-0.1.0.dist-info/RECORD
