Metadata-Version: 2.1
Name: deepexperiment
Version: 0.1.0
Summary: A simple deep learning experiment function
Author: Kimino namae
Author-email: expvpn235@gmail.com
Classifier: Programming Language :: Python :: 3
Classifier: Operating System :: OS Independent
Requires-Python: >=3.6
